dstack/__init__.py
dstack/version.py
dstack/_internal/__init__.py
dstack/_internal/compat.py
dstack/_internal/settings.py
dstack/_internal/cli/__init__.py
dstack/_internal/cli/main.py
dstack/_internal/cli/commands/__init__.py
dstack/_internal/cli/commands/apply.py
dstack/_internal/cli/commands/attach.py
dstack/_internal/cli/commands/completion.py
dstack/_internal/cli/commands/delete.py
dstack/_internal/cli/commands/event.py
dstack/_internal/cli/commands/fleet.py
dstack/_internal/cli/commands/gateway.py
dstack/_internal/cli/commands/init.py
dstack/_internal/cli/commands/login.py
dstack/_internal/cli/commands/logs.py
dstack/_internal/cli/commands/metrics.py
dstack/_internal/cli/commands/offer.py
dstack/_internal/cli/commands/project.py
dstack/_internal/cli/commands/ps.py
dstack/_internal/cli/commands/run.py
dstack/_internal/cli/commands/secrets.py
dstack/_internal/cli/commands/server.py
dstack/_internal/cli/commands/stop.py
dstack/_internal/cli/commands/volume.py
dstack/_internal/cli/models/__init__.py
dstack/_internal/cli/models/gateways.py
dstack/_internal/cli/models/offers.py
dstack/_internal/cli/models/runs.py
dstack/_internal/cli/services/__init__.py
dstack/_internal/cli/services/args.py
dstack/_internal/cli/services/completion.py
dstack/_internal/cli/services/events.py
dstack/_internal/cli/services/profile.py
dstack/_internal/cli/services/repos.py
dstack/_internal/cli/services/configurators/__init__.py
dstack/_internal/cli/services/configurators/base.py
dstack/_internal/cli/services/configurators/fleet.py
dstack/_internal/cli/services/configurators/gateway.py
dstack/_internal/cli/services/configurators/run.py
dstack/_internal/cli/services/configurators/volume.py
dstack/_internal/cli/utils/__init__.py
dstack/_internal/cli/utils/common.py
dstack/_internal/cli/utils/fleet.py
dstack/_internal/cli/utils/gateway.py
dstack/_internal/cli/utils/gpu.py
dstack/_internal/cli/utils/rich.py
dstack/_internal/cli/utils/run.py
dstack/_internal/cli/utils/secrets.py
dstack-0.20.3.dist-info/METADATA
dstack-0.20.3.dist-info/WHEEL
dstack-0.20.3.dist-info/entry_points.txt
dstack-0.20.3.dist-info/licenses/LICENSE.md
dstack-0.20.3.dist-info/RECORD
