Metadata-Version: 2.4
Name: dstack
Version: 0.20.3
Summary: dstack is an open-source orchestration engine for running AI workloads on any cloud or on-premises.
Project-URL: Homepage, https://dstack.ai
Project-URL: Source, https://github.com/dstackai/dstack
Project-URL: Documentation, https://dstack.ai/docs
Project-URL: Issues, https://github.com/dstackai/dstack/issues
Project-URL: Changelog, https://github.com/dstackai/dstack/releases
Project-URL: Discord, https://discord.gg/u8SmfwPpMd
Author-email: Andrey Cheptsov <andrey@dstack.ai>
License-File: LICENSE.md
Classifier: Development Status :: 4 - Beta
Classifier: License :: OSI Approved :: Mozilla Public License 2.0 (MPL 2.0)
Classifier: Programming Language :: Python :: 3
Classifier: Topic :: Scientific/Engineering :: Artificial Intelligence
Requires-Python: >=3.9
Requires-Dist: apscheduler<4
Requires-Dist: argcomplete>=3.5.0
Requires-Dist: cachetools
Requires-Dist: cryptography
Requires-Dist: cursor
Requires-Dist: filelock
Requires-Dist: gitpython
Requires-Dist: gpuhunt==0.1.16
Requires-Dist: ignore-python>=0.2.0
Requires-Dist: jsonschema
Requires-Dist: orjson
Requires-Dist: packaging
Requires-Dist: paramiko>=3.2.0
Requires-Dist: psutil
Requires-Dist: pydantic-duality>=1.2.4
Requires-Dist: pydantic<2.0.0,>=1.10.10
Requires-Dist: python-dateutil
Requires-Dist: python-multipart>=0.0.16
Requires-Dist: pyyaml
Requires-Dist: requests
Requires-Dist: rich
Requires-Dist: rich-argparse
Requires-Dist: simple-term-menu
Requires-Dist: tqdm
Requires-Dist: typing-extensions>=4.0.0
Requires-Dist: websocket-client
Provides-Extra: all
Requires-Dist: aiocache; extra == 'all'
Requires-Dist: aiorwlock; extra == 'all'
Requires-Dist: aiosqlite; extra == 'all'
Requires-Dist: alembic-postgresql-enum; extra == 'all'
Requires-Dist: alembic>=1.16.0; extra == 'all'
Requires-Dist: asyncpg; extra == 'all'
Requires-Dist: azure-identity>=1.12.0; extra == 'all'
Requires-Dist: azure-mgmt-authorization>=3.0.0; extra == 'all'
Requires-Dist: azure-mgmt-compute>=29.1.0; extra == 'all'
Requires-Dist: azure-mgmt-msi>=7.0.0; extra == 'all'
Requires-Dist: azure-mgmt-network<28.0.0,>=23.0.0; extra == 'all'
Requires-Dist: azure-mgmt-resource>=22.0.0; extra == 'all'
Requires-Dist: azure-mgmt-subscription>=3.1.1; extra == 'all'
Requires-Dist: backports-entry-points-selectable; extra == 'all'
Requires-Dist: boto3>=1.38.13; extra == 'all'
Requires-Dist: botocore; extra == 'all'
Requires-Dist: cryptography>=44.0.3; extra == 'all'
Requires-Dist: docker>=6.0.0; extra == 'all'
Requires-Dist: fastapi; extra == 'all'
Requires-Dist: google-api-python-client>=2.80.0; extra == 'all'
Requires-Dist: google-auth>=2.3.0; extra == 'all'
Requires-Dist: google-cloud-billing>=1.11.0; extra == 'all'
Requires-Dist: google-cloud-compute>=1.5.0; extra == 'all'
Requires-Dist: google-cloud-logging>=2.0.0; extra == 'all'
Requires-Dist: google-cloud-storage>=2.0.0; extra == 'all'
Requires-Dist: google-cloud-tpu>=1.18.3; extra == 'all'
Requires-Dist: grpcio>=1.50; extra == 'all'
Requires-Dist: httpx>=0.28.0; extra == 'all'
Requires-Dist: jinja2; extra == 'all'
Requires-Dist: kubernetes; extra == 'all'
Requires-Dist: nebius<0.4,>=0.3.4; (python_version >= '3.10') and extra == 'all'
Requires-Dist: oci>=2.150.0; extra == 'all'
Requires-Dist: prometheus-client; extra == 'all'
Requires-Dist: pyopenssl>=23.2.0; extra == 'all'
Requires-Dist: python-dxf>=12.1.1; extra == 'all'
Requires-Dist: python-json-logger>=3.1.0; extra == 'all'
Requires-Dist: sentry-sdk[fastapi]>=2.27.0; extra == 'all'
Requires-Dist: sqlalchemy-utils>=0.40.0; extra == 'all'
Requires-Dist: sqlalchemy[asyncio]>=2.0.0; extra == 'all'
Requires-Dist: starlette>=0.26.0; extra == 'all'
Requires-Dist: uvicorn; extra == 'all'
Requires-Dist: uvicorn[standard]; extra == 'all'
Requires-Dist: verda; (python_version >= '3.10') and extra == 'all'
Requires-Dist: watchfiles; extra == 'all'
Provides-Extra: aws
Requires-Dist: aiocache; extra == 'aws'
Requires-Dist: aiorwlock; extra == 'aws'
Requires-Dist: aiosqlite; extra == 'aws'
Requires-Dist: alembic-postgresql-enum; extra == 'aws'
Requires-Dist: alembic>=1.16.0; extra == 'aws'
Requires-Dist: asyncpg; extra == 'aws'
Requires-Dist: backports-entry-points-selectable; extra == 'aws'
Requires-Dist: boto3>=1.38.13; extra == 'aws'
Requires-Dist: botocore; extra == 'aws'
Requires-Dist: docker>=6.0.0; extra == 'aws'
Requires-Dist: fastapi; extra == 'aws'
Requires-Dist: grpcio>=1.50; extra == 'aws'
Requires-Dist: httpx>=0.28.0; extra == 'aws'
Requires-Dist: jinja2; extra == 'aws'
Requires-Dist: prometheus-client; extra == 'aws'
Requires-Dist: python-dxf>=12.1.1; extra == 'aws'
Requires-Dist: python-json-logger>=3.1.0; extra == 'aws'
Requires-Dist: sentry-sdk[fastapi]>=2.27.0; extra == 'aws'
Requires-Dist: sqlalchemy-utils>=0.40.0; extra == 'aws'
Requires-Dist: sqlalchemy[asyncio]>=2.0.0; extra == 'aws'
Requires-Dist: starlette>=0.26.0; extra == 'aws'
Requires-Dist: uvicorn[standard]; extra == 'aws'
Requires-Dist: watchfiles; extra == 'aws'
Provides-Extra: azure
Requires-Dist: aiocache; extra == 'azure'
Requires-Dist: aiorwlock; extra == 'azure'
Requires-Dist: aiosqlite; extra == 'azure'
Requires-Dist: alembic-postgresql-enum; extra == 'azure'
Requires-Dist: alembic>=1.16.0; extra == 'azure'
Requires-Dist: asyncpg; extra == 'azure'
Requires-Dist: azure-identity>=1.12.0; extra == 'azure'
Requires-Dist: azure-mgmt-authorization>=3.0.0; extra == 'azure'
Requires-Dist: azure-mgmt-compute>=29.1.0; extra == 'azure'
Requires-Dist: azure-mgmt-msi>=7.0.0; extra == 'azure'
Requires-Dist: azure-mgmt-network<28.0.0,>=23.0.0; extra == 'azure'
Requires-Dist: azure-mgmt-resource>=22.0.0; extra == 'azure'
Requires-Dist: azure-mgmt-subscription>=3.1.1; extra == 'azure'
Requires-Dist: backports-entry-points-selectable; extra == 'azure'
Requires-Dist: docker>=6.0.0; extra == 'azure'
Requires-Dist: fastapi; extra == 'azure'
Requires-Dist: grpcio>=1.50; extra == 'azure'
Requires-Dist: httpx>=0.28.0; extra == 'azure'
Requires-Dist: jinja2; extra == 'azure'
Requires-Dist: prometheus-client; extra == 'azure'
Requires-Dist: python-dxf>=12.1.1; extra == 'azure'
Requires-Dist: python-json-logger>=3.1.0; extra == 'azure'
Requires-Dist: sentry-sdk[fastapi]>=2.27.0; extra == 'azure'
Requires-Dist: sqlalchemy-utils>=0.40.0; extra == 'azure'
Requires-Dist: sqlalchemy[asyncio]>=2.0.0; extra == 'azure'
Requires-Dist: starlette>=0.26.0; extra == 'azure'
Requires-Dist: uvicorn[standard]; extra == 'azure'
Requires-Dist: watchfiles; extra == 'azure'
Provides-Extra: datacrunch
Requires-Dist: aiocache; extra == 'datacrunch'
Requires-Dist: aiorwlock; extra == 'datacrunch'
Requires-Dist: aiosqlite; extra == 'datacrunch'
Requires-Dist: alembic-postgresql-enum; extra == 'datacrunch'
Requires-Dist: alembic>=1.16.0; extra == 'datacrunch'
Requires-Dist: asyncpg; extra == 'datacrunch'
Requires-Dist: backports-entry-points-selectable; extra == 'datacrunch'
Requires-Dist: docker>=6.0.0; extra == 'datacrunch'
Requires-Dist: fastapi; extra == 'datacrunch'
Requires-Dist: grpcio>=1.50; extra == 'datacrunch'
Requires-Dist: httpx>=0.28.0; extra == 'datacrunch'
Requires-Dist: jinja2; extra == 'datacrunch'
Requires-Dist: prometheus-client; extra == 'datacrunch'
Requires-Dist: python-dxf>=12.1.1; extra == 'datacrunch'
Requires-Dist: python-json-logger>=3.1.0; extra == 'datacrunch'
Requires-Dist: sentry-sdk[fastapi]>=2.27.0; extra == 'datacrunch'
Requires-Dist: sqlalchemy-utils>=0.40.0; extra == 'datacrunch'
Requires-Dist: sqlalchemy[asyncio]>=2.0.0; extra == 'datacrunch'
Requires-Dist: starlette>=0.26.0; extra == 'datacrunch'
Requires-Dist: uvicorn[standard]; extra == 'datacrunch'
Requires-Dist: verda; (python_version >= '3.10') and extra == 'datacrunch'
Requires-Dist: watchfiles; extra == 'datacrunch'
Provides-Extra: gateway
Requires-Dist: aiocache; extra == 'gateway'
Requires-Dist: aiorwlock; extra == 'gateway'
Requires-Dist: fastapi; extra == 'gateway'
Requires-Dist: httpx>=0.28.0; extra == 'gateway'
Requires-Dist: jinja2; extra == 'gateway'
Requires-Dist: starlette>=0.26.0; extra == 'gateway'
Requires-Dist: uvicorn; extra == 'gateway'
Provides-Extra: gcp
Requires-Dist: aiocache; extra == 'gcp'
Requires-Dist: aiorwlock; extra == 'gcp'
Requires-Dist: aiosqlite; extra == 'gcp'
Requires-Dist: alembic-postgresql-enum; extra == 'gcp'
Requires-Dist: alembic>=1.16.0; extra == 'gcp'
Requires-Dist: asyncpg; extra == 'gcp'
Requires-Dist: backports-entry-points-selectable; extra == 'gcp'
Requires-Dist: docker>=6.0.0; extra == 'gcp'
Requires-Dist: fastapi; extra == 'gcp'
Requires-Dist: google-api-python-client>=2.80.0; extra == 'gcp'
Requires-Dist: google-auth>=2.3.0; extra == 'gcp'
Requires-Dist: google-cloud-billing>=1.11.0; extra == 'gcp'
Requires-Dist: google-cloud-compute>=1.5.0; extra == 'gcp'
Requires-Dist: google-cloud-logging>=2.0.0; extra == 'gcp'
Requires-Dist: google-cloud-storage>=2.0.0; extra == 'gcp'
Requires-Dist: google-cloud-tpu>=1.18.3; extra == 'gcp'
Requires-Dist: grpcio>=1.50; extra == 'gcp'
Requires-Dist: httpx>=0.28.0; extra == 'gcp'
Requires-Dist: jinja2; extra == 'gcp'
Requires-Dist: prometheus-client; extra == 'gcp'
Requires-Dist: python-dxf>=12.1.1; extra == 'gcp'
Requires-Dist: python-json-logger>=3.1.0; extra == 'gcp'
Requires-Dist: sentry-sdk[fastapi]>=2.27.0; extra == 'gcp'
Requires-Dist: sqlalchemy-utils>=0.40.0; extra == 'gcp'
Requires-Dist: sqlalchemy[asyncio]>=2.0.0; extra == 'gcp'
Requires-Dist: starlette>=0.26.0; extra == 'gcp'
Requires-Dist: uvicorn[standard]; extra == 'gcp'
Requires-Dist: watchfiles; extra == 'gcp'
Provides-Extra: kubernetes
Requires-Dist: aiocache; extra == 'kubernetes'
Requires-Dist: aiorwlock; extra == 'kubernetes'
Requires-Dist: aiosqlite; extra == 'kubernetes'
Requires-Dist: alembic-postgresql-enum; extra == 'kubernetes'
Requires-Dist: alembic>=1.16.0; extra == 'kubernetes'
Requires-Dist: asyncpg; extra == 'kubernetes'
Requires-Dist: backports-entry-points-selectable; extra == 'kubernetes'
Requires-Dist: docker>=6.0.0; extra == 'kubernetes'
Requires-Dist: fastapi; extra == 'kubernetes'
Requires-Dist: grpcio>=1.50; extra == 'kubernetes'
Requires-Dist: httpx>=0.28.0; extra == 'kubernetes'
Requires-Dist: jinja2; extra == 'kubernetes'
Requires-Dist: kubernetes; extra == 'kubernetes'
Requires-Dist: prometheus-client; extra == 'kubernetes'
Requires-Dist: python-dxf>=12.1.1; extra == 'kubernetes'
Requires-Dist: python-json-logger>=3.1.0; extra == 'kubernetes'
Requires-Dist: sentry-sdk[fastapi]>=2.27.0; extra == 'kubernetes'
Requires-Dist: sqlalchemy-utils>=0.40.0; extra == 'kubernetes'
Requires-Dist: sqlalchemy[asyncio]>=2.0.0; extra == 'kubernetes'
Requires-Dist: starlette>=0.26.0; extra == 'kubernetes'
Requires-Dist: uvicorn[standard]; extra == 'kubernetes'
Requires-Dist: watchfiles; extra == 'kubernetes'
Provides-Extra: lambda
Requires-Dist: aiocache; extra == 'lambda'
Requires-Dist: aiorwlock; extra == 'lambda'
Requires-Dist: aiosqlite; extra == 'lambda'
Requires-Dist: alembic-postgresql-enum; extra == 'lambda'
Requires-Dist: alembic>=1.16.0; extra == 'lambda'
Requires-Dist: asyncpg; extra == 'lambda'
Requires-Dist: backports-entry-points-selectable; extra == 'lambda'
Requires-Dist: boto3>=1.38.13; extra == 'lambda'
Requires-Dist: botocore; extra == 'lambda'
Requires-Dist: docker>=6.0.0; extra == 'lambda'
Requires-Dist: fastapi; extra == 'lambda'
Requires-Dist: grpcio>=1.50; extra == 'lambda'
Requires-Dist: httpx>=0.28.0; extra == 'lambda'
Requires-Dist: jinja2; extra == 'lambda'
Requires-Dist: prometheus-client; extra == 'lambda'
Requires-Dist: python-dxf>=12.1.1; extra == 'lambda'
Requires-Dist: python-json-logger>=3.1.0; extra == 'lambda'
Requires-Dist: sentry-sdk[fastapi]>=2.27.0; extra == 'lambda'
Requires-Dist: sqlalchemy-utils>=0.40.0; extra == 'lambda'
Requires-Dist: sqlalchemy[asyncio]>=2.0.0; extra == 'lambda'
Requires-Dist: starlette>=0.26.0; extra == 'lambda'
Requires-Dist: uvicorn[standard]; extra == 'lambda'
Requires-Dist: watchfiles; extra == 'lambda'
Provides-Extra: nebius
Requires-Dist: aiocache; extra == 'nebius'
Requires-Dist: aiorwlock; extra == 'nebius'
Requires-Dist: aiosqlite; extra == 'nebius'
Requires-Dist: alembic-postgresql-enum; extra == 'nebius'
Requires-Dist: alembic>=1.16.0; extra == 'nebius'
Requires-Dist: asyncpg; extra == 'nebius'
Requires-Dist: backports-entry-points-selectable; extra == 'nebius'
Requires-Dist: docker>=6.0.0; extra == 'nebius'
Requires-Dist: fastapi; extra == 'nebius'
Requires-Dist: grpcio>=1.50; extra == 'nebius'
Requires-Dist: httpx>=0.28.0; extra == 'nebius'
Requires-Dist: jinja2; extra == 'nebius'
Requires-Dist: nebius<0.4,>=0.3.4; (python_version >= '3.10') and extra == 'nebius'
Requires-Dist: prometheus-client; extra == 'nebius'
Requires-Dist: python-dxf>=12.1.1; extra == 'nebius'
Requires-Dist: python-json-logger>=3.1.0; extra == 'nebius'
Requires-Dist: sentry-sdk[fastapi]>=2.27.0; extra == 'nebius'
Requires-Dist: sqlalchemy-utils>=0.40.0; extra == 'nebius'
Requires-Dist: sqlalchemy[asyncio]>=2.0.0; extra == 'nebius'
Requires-Dist: starlette>=0.26.0; extra == 'nebius'
Requires-Dist: uvicorn[standard]; extra == 'nebius'
Requires-Dist: watchfiles; extra == 'nebius'
Provides-Extra: oci
Requires-Dist: aiocache; extra == 'oci'
Requires-Dist: aiorwlock; extra == 'oci'
Requires-Dist: aiosqlite; extra == 'oci'
Requires-Dist: alembic-postgresql-enum; extra == 'oci'
Requires-Dist: alembic>=1.16.0; extra == 'oci'
Requires-Dist: asyncpg; extra == 'oci'
Requires-Dist: backports-entry-points-selectable; extra == 'oci'
Requires-Dist: cryptography>=44.0.3; extra == 'oci'
Requires-Dist: docker>=6.0.0; extra == 'oci'
Requires-Dist: fastapi; extra == 'oci'
Requires-Dist: grpcio>=1.50; extra == 'oci'
Requires-Dist: httpx>=0.28.0; extra == 'oci'
Requires-Dist: jinja2; extra == 'oci'
Requires-Dist: oci>=2.150.0; extra == 'oci'
Requires-Dist: prometheus-client; extra == 'oci'
Requires-Dist: pyopenssl>=23.2.0; extra == 'oci'
Requires-Dist: python-dxf>=12.1.1; extra == 'oci'
Requires-Dist: python-json-logger>=3.1.0; extra == 'oci'
Requires-Dist: sentry-sdk[fastapi]>=2.27.0; extra == 'oci'
Requires-Dist: sqlalchemy-utils>=0.40.0; extra == 'oci'
Requires-Dist: sqlalchemy[asyncio]>=2.0.0; extra == 'oci'
Requires-Dist: starlette>=0.26.0; extra == 'oci'
Requires-Dist: uvicorn[standard]; extra == 'oci'
Requires-Dist: watchfiles; extra == 'oci'
Provides-Extra: server
Requires-Dist: aiocache; extra == 'server'
Requires-Dist: aiorwlock; extra == 'server'
Requires-Dist: aiosqlite; extra == 'server'
Requires-Dist: alembic-postgresql-enum; extra == 'server'
Requires-Dist: alembic>=1.16.0; extra == 'server'
Requires-Dist: asyncpg; extra == 'server'
Requires-Dist: backports-entry-points-selectable; extra == 'server'
Requires-Dist: docker>=6.0.0; extra == 'server'
Requires-Dist: fastapi; extra == 'server'
Requires-Dist: grpcio>=1.50; extra == 'server'
Requires-Dist: httpx>=0.28.0; extra == 'server'
Requires-Dist: jinja2; extra == 'server'
Requires-Dist: prometheus-client; extra == 'server'
Requires-Dist: python-dxf>=12.1.1; extra == 'server'
Requires-Dist: python-json-logger>=3.1.0; extra == 'server'
Requires-Dist: sentry-sdk[fastapi]>=2.27.0; extra == 'server'
Requires-Dist: sqlalchemy-utils>=0.40.0; extra == 'server'
Requires-Dist: sqlalchemy[asyncio]>=2.0.0; extra == 'server'
Requires-Dist: starlette>=0.26.0; extra == 'server'
Requires-Dist: uvicorn[standard]; extra == 'server'
Requires-Dist: watchfiles; extra == 'server'
Provides-Extra: verda
Requires-Dist: aiocache; extra == 'verda'
Requires-Dist: aiorwlock; extra == 'verda'
Requires-Dist: aiosqlite; extra == 'verda'
Requires-Dist: alembic-postgresql-enum; extra == 'verda'
Requires-Dist: alembic>=1.16.0; extra == 'verda'
Requires-Dist: asyncpg; extra == 'verda'
Requires-Dist: backports-entry-points-selectable; extra == 'verda'
Requires-Dist: docker>=6.0.0; extra == 'verda'
Requires-Dist: fastapi; extra == 'verda'
Requires-Dist: grpcio>=1.50; extra == 'verda'
Requires-Dist: httpx>=0.28.0; extra == 'verda'
Requires-Dist: jinja2; extra == 'verda'
Requires-Dist: prometheus-client; extra == 'verda'
Requires-Dist: python-dxf>=12.1.1; extra == 'verda'
Requires-Dist: python-json-logger>=3.1.0; extra == 'verda'
Requires-Dist: sentry-sdk[fastapi]>=2.27.0; extra == 'verda'
Requires-Dist: sqlalchemy-utils>=0.40.0; extra == 'verda'
Requires-Dist: sqlalchemy[asyncio]>=2.0.0; extra == 'verda'
Requires-Dist: starlette>=0.26.0; extra == 'verda'
Requires-Dist: uvicorn[standard]; extra == 'verda'
Requires-Dist: verda; (python_version >= '3.10') and extra == 'verda'
Requires-Dist: watchfiles; extra == 'verda'
